{
    "89bbd920-f9c6-f1ee-242f-3626b04d0141": {
        "paletteKey": "FlexLayoutCol",
        "commentid": null,
        "designerReference": [
            {
                "_key": "componentLabel",
                "_value": "Column",
                "_type": "kv",
                "_attrDef": "p",
                "_useAsLabel": true
            },
            {
                "_key": "style",
                "_value": "",
                "_type": "kv",
                "_attrDef": "p"
            },
            {
                "_key": "class",
                "_value": "",
                "_type": "dav",
                "_attrDef": "p"
            },
            {
                "_key": "fxFlex",
                "_value": "",
                "_type": "kv",
                "_attrDef": "p"
            },
            {
                "_key": "fxLayoutGap",
                "_value": "",
                "_type": "kv",
                "_attrDef": "p"
            },
            {
                "_key": "wrap",
                "_value": "wrap",
                "_type": "a",
                "_attrDef": "p"
            },
            {
                "_key": "layoutAlign",
                "_value": "start",
                "_type": "a",
                "_attrDef": "p"
            },
            {
                "_key": "pLayoutAlign",
                "_value": "stretch",
                "_type": "a",
                "_attrDef": "p"
            },
            {
                "_key": "[fxShow]",
                "_value": "true",
                "_type": "kv",
                "_attrDef": "p"
            }
        ],
        "3d9fd14b-63c9-2d5b-a1d8-66749818231a": {
            "paletteKey": "FlexLayoutRow",
            "parentEditorKey": "89bbd920-f9c6-f1ee-242f-3626b04d0141",
            "commentid": null,
            "designerReference": [
                {
                    "_key": "componentLabel",
                    "_value": "Row",
                    "_type": "kv",
                    "_attrDef": "p",
                    "_useAsLabel": true
                },
                {
                    "_key": "style",
                    "_value": "",
                    "_type": "kv",
                    "_attrDef": "p"
                },
                {
                    "_key": "class",
                    "_value": "",
                    "_type": "dav",
                    "_attrDef": "p"
                },
                {
                    "_key": "fxFlex",
                    "_value": "",
                    "_type": "kv",
                    "_attrDef": "p"
                },
                {
                    "_key": "fxLayoutGap",
                    "_value": "",
                    "_type": "kv",
                    "_attrDef": "p"
                },
                {
                    "_key": "wrap",
                    "_value": "wrap",
                    "_type": "a",
                    "_attrDef": "p"
                },
                {
                    "_key": "layoutAlign",
                    "_value": "start",
                    "_type": "a",
                    "_attrDef": "p"
                },
                {
                    "_key": "pLayoutAlign",
                    "_value": "stretch",
                    "_type": "a",
                    "_attrDef": "p"
                },
                {
                    "_key": "[fxShow]",
                    "_value": "true",
                    "_type": "kv",
                    "_attrDef": "p"
                }
            ],
            "73e7468a-4397-662b-20f0-ae8ac986a45d": {
                "paletteKey": "FlexLayoutCol",
                "parentEditorKey": "3d9fd14b-63c9-2d5b-a1d8-66749818231a",
                "commentid": null,
                "designerReference": [
                    {
                        "_key": "componentLabel",
                        "_value": "Column",
                        "_type": "kv",
                        "_attrDef": "p",
                        "_useAsLabel": true
                    },
                    {
                        "_key": "style",
                        "_value": "",
                        "_type": "kv",
                        "_attrDef": "p"
                    },
                    {
                        "_key": "class",
                        "_value": "",
                        "_type": "dav",
                        "_attrDef": "p"
                    },
                    {
                        "_key": "fxFlex",
                        "_value": "",
                        "_type": "kv",
                        "_attrDef": "p"
                    },
                    {
                        "_key": "fxLayoutGap",
                        "_value": "",
                        "_type": "kv",
                        "_attrDef": "p"
                    },
                    {
                        "_key": "wrap",
                        "_value": "wrap",
                        "_type": "a",
                        "_attrDef": "p"
                    },
                    {
                        "_key": "layoutAlign",
                        "_value": "start",
                        "_type": "a",
                        "_attrDef": "p"
                    },
                    {
                        "_key": "pLayoutAlign",
                        "_value": "stretch",
                        "_type": "a",
                        "_attrDef": "p"
                    },
                    {
                        "_key": "[fxShow]",
                        "_value": "true",
                        "_type": "kv",
                        "_attrDef": "p"
                    }
                ],
                "0fd3bd63-aae9-ec5c-9486-a1db26c31ee1": {
                    "paletteKey": "Html5",
                    "parentEditorKey": "73e7468a-4397-662b-20f0-ae8ac986a45d",
                    "isAdvancedComponent": true,
                    "commentid": null,
                    "designerReference": [
                        {
                            "_key": "style",
                            "_value": "",
                            "_type": "kv",
                            "_attrDef": "p"
                        },
                        {
                            "_key": "class",
                            "_value": "",
                            "_type": "dav",
                            "_attrDef": "p"
                        },
                        {
                            "_key": "htmlElement",
                            "_value": "h3",
                            "_type": "dav",
                            "_attrDef": "p",
                            "_useAsLabel": true
                        },
                        {
                            "_key": "tagType",
                            "_value": "h3",
                            "_type": "a",
                            "_attrDef": "p",
                            "_visibility": false
                        },
                        {
                            "_key": "name",
                            "_value": "",
                            "_type": "kv",
                            "_attrDef": "p",
                            "_visibility": false
                        },
                        {
                            "_key": "sandbox",
                            "_value": "",
                            "_type": "kv",
                            "_attrDef": "p",
                            "_visibility": false
                        },
                        {
                            "_key": "src",
                            "_value": "",
                            "_type": "kv",
                            "_attrDef": "p",
                            "_visibility": false
                        },
                        {
                            "_key": "srcdoc",
                            "_value": "",
                            "_type": "kv",
                            "_attrDef": "p",
                            "_visibility": false
                        },
                        {
                            "_key": "width",
                            "_value": "",
                            "_type": "kv",
                            "_attrDef": "p",
                            "_visibility": false
                        },
                        {
                            "_key": "[autoplay]",
                            "_value": "",
                            "_type": "kv",
                            "_attrDef": "p",
                            "_visibility": false
                        },
                        {
                            "_key": "[loop]",
                            "_value": "",
                            "_type": "kv",
                            "_attrDef": "p",
                            "_visibility": false
                        },
                        {
                            "_key": "data",
                            "_value": "",
                            "_type": "kv",
                            "_attrDef": "p",
                            "_visibility": false
                        },
                        {
                            "_key": "audioSource",
                            "_value": [],
                            "_type": "a",
                            "_attrDef": "p",
                            "_visibility": false
                        },
                        {
                            "_key": "videoSource",
                            "_value": [],
                            "_type": "a",
                            "_attrDef": "p",
                            "_visibility": false
                        },
                        {
                            "_key": "audioDatasource",
                            "_value": "",
                            "_type": "a",
                            "_attrDef": "p",
                            "_visibility": false
                        },
                        {
                            "_key": "audioSrc",
                            "_value": "",
                            "_type": "a",
                            "_attrDef": "p",
                            "_visibility": false
                        },
                        {
                            "_key": "audioType",
                            "_value": "",
                            "_type": "a",
                            "_attrDef": "p",
                            "_visibility": false
                        },
                        {
                            "_key": "videoDatasource",
                            "_value": "",
                            "_type": "a",
                            "_attrDef": "p",
                            "_visibility": false
                        },
                        {
                            "_key": "videoSrc",
                            "_value": "",
                            "_type": "a",
                            "_attrDef": "p",
                            "_visibility": false
                        },
                        {
                            "_key": "videoType",
                            "_value": "",
                            "_type": "a",
                            "_attrDef": "p",
                            "_visibility": false
                        },
                        {
                            "_key": "(audioplay)",
                            "_value": "",
                            "_type": "a",
                            "_attrDef": "p",
                            "_visibility": false
                        },
                        {
                            "_key": "(videoplay)",
                            "_value": "",
                            "_type": "a",
                            "_attrDef": "p",
                            "_visibility": false
                        },
                        {
                            "_key": "(audiopause)",
                            "_value": "",
                            "_type": "kv",
                            "_attrDef": "p",
                            "_visibility": false
                        },
                        {
                            "_key": "(videopause)",
                            "_value": "",
                            "_type": "kv",
                            "_attrDef": "p",
                            "_visibility": false
                        },
                        {
                            "_key": "(audioended)",
                            "_value": "",
                            "_type": "kv",
                            "_attrDef": "p",
                            "_visibility": false
                        },
                        {
                            "_key": "(videoended)",
                            "_value": "",
                            "_type": "kv",
                            "_attrDef": "p",
                            "_visibility": false
                        }
                    ],
                    "c2b12994-3e4c-8a9d-b59f-1634dd463e5a": {
                        "paletteKey": "html-editor",
                        "parentEditorKey": "0fd3bd63-aae9-ec5c-9486-a1db26c31ee1",
                        "isAdvancedChildComponent": true,
                        "commentid": null,
                        "designerReference": [
                            {
                                "_key": "style",
                                "_value": "",
                                "_type": "kv",
                                "_attrDef": "p"
                            },
                            {
                                "_key": "class",
                                "_value": "",
                                "_type": "dav",
                                "_attrDef": "p"
                            },
                            {
                                "_key": "html",
                                "_value": "",
                                "_type": "a",
                                "_attrDef": "p"
                            }
                        ]
                    }
                }
            },
            "f1e211df-524e-b543-61a6-8f4ffefb8abd": {
                "paletteKey": "FlexLayoutCol",
                "parentEditorKey": "3d9fd14b-63c9-2d5b-a1d8-66749818231a",
                "commentid": null,
                "designerReference": [
                    {
                        "_key": "componentLabel",
                        "_value": "Column",
                        "_type": "kv",
                        "_attrDef": "p",
                        "_useAsLabel": true
                    },
                    {
                        "_key": "style",
                        "_value": "",
                        "_type": "kv",
                        "_attrDef": "p"
                    },
                    {
                        "_key": "class",
                        "_value": "",
                        "_type": "dav",
                        "_attrDef": "p"
                    },
                    {
                        "_key": "fxFlex",
                        "_value": "",
                        "_type": "kv",
                        "_attrDef": "p"
                    },
                    {
                        "_key": "fxLayoutGap",
                        "_value": "",
                        "_type": "kv",
                        "_attrDef": "p"
                    },
                    {
                        "_key": "wrap",
                        "_value": "wrap",
                        "_type": "a",
                        "_attrDef": "p"
                    },
                    {
                        "_key": "layoutAlign",
                        "_value": "start",
                        "_type": "a",
                        "_attrDef": "p"
                    },
                    {
                        "_key": "pLayoutAlign",
                        "_value": "stretch",
                        "_type": "a",
                        "_attrDef": "p"
                    },
                    {
                        "_key": "[fxShow]",
                        "_value": "true",
                        "_type": "kv",
                        "_attrDef": "p"
                    }
                ],
                "643c0549-a468-bcae-b5b6-49138e925b10": {
                    "paletteKey": "Html5",
                    "parentEditorKey": "f1e211df-524e-b543-61a6-8f4ffefb8abd",
                    "isAdvancedComponent": true,
                    "commentid": null,
                    "designerReference": [
                        {
                            "_key": "style",
                            "_value": "",
                            "_type": "kv",
                            "_attrDef": "p"
                        },
                        {
                            "_key": "class",
                            "_value": "",
                            "_type": "dav",
                            "_attrDef": "p"
                        },
                        {
                            "_key": "htmlElement",
                            "_value": "div",
                            "_type": "dav",
                            "_attrDef": "p",
                            "_useAsLabel": true
                        },
                        {
                            "_key": "tagType",
                            "_value": "",
                            "_type": "a",
                            "_attrDef": "p",
                            "_visibility": false
                        },
                        {
                            "_key": "name",
                            "_value": "",
                            "_type": "kv",
                            "_attrDef": "p",
                            "_visibility": false
                        },
                        {
                            "_key": "sandbox",
                            "_value": "",
                            "_type": "kv",
                            "_attrDef": "p",
                            "_visibility": false
                        },
                        {
                            "_key": "src",
                            "_value": "",
                            "_type": "kv",
                            "_attrDef": "p",
                            "_visibility": false
                        },
                        {
                            "_key": "srcdoc",
                            "_value": "",
                            "_type": "kv",
                            "_attrDef": "p",
                            "_visibility": false
                        },
                        {
                            "_key": "width",
                            "_value": "",
                            "_type": "kv",
                            "_attrDef": "p",
                            "_visibility": false
                        },
                        {
                            "_key": "[autoplay]",
                            "_value": "",
                            "_type": "kv",
                            "_attrDef": "p",
                            "_visibility": false
                        },
                        {
                            "_key": "[loop]",
                            "_value": "",
                            "_type": "kv",
                            "_attrDef": "p",
                            "_visibility": false
                        },
                        {
                            "_key": "data",
                            "_value": "",
                            "_type": "kv",
                            "_attrDef": "p",
                            "_visibility": false
                        },
                        {
                            "_key": "audioSource",
                            "_value": [],
                            "_type": "a",
                            "_attrDef": "p",
                            "_visibility": false
                        },
                        {
                            "_key": "videoSource",
                            "_value": [],
                            "_type": "a",
                            "_attrDef": "p",
                            "_visibility": false
                        },
                        {
                            "_key": "audioDatasource",
                            "_value": "",
                            "_type": "a",
                            "_attrDef": "p",
                            "_visibility": false
                        },
                        {
                            "_key": "audioSrc",
                            "_value": "",
                            "_type": "a",
                            "_attrDef": "p",
                            "_visibility": false
                        },
                        {
                            "_key": "audioType",
                            "_value": "",
                            "_type": "a",
                            "_attrDef": "p",
                            "_visibility": false
                        },
                        {
                            "_key": "videoDatasource",
                            "_value": "",
                            "_type": "a",
                            "_attrDef": "p",
                            "_visibility": false
                        },
                        {
                            "_key": "videoSrc",
                            "_value": "",
                            "_type": "a",
                            "_attrDef": "p",
                            "_visibility": false
                        },
                        {
                            "_key": "videoType",
                            "_value": "",
                            "_type": "a",
                            "_attrDef": "p",
                            "_visibility": false
                        },
                        {
                            "_key": "(audioplay)",
                            "_value": "",
                            "_type": "a",
                            "_attrDef": "p",
                            "_visibility": false
                        },
                        {
                            "_key": "(videoplay)",
                            "_value": "",
                            "_type": "a",
                            "_attrDef": "p",
                            "_visibility": false
                        },
                        {
                            "_key": "(audiopause)",
                            "_value": "",
                            "_type": "kv",
                            "_attrDef": "p",
                            "_visibility": false
                        },
                        {
                            "_key": "(videopause)",
                            "_value": "",
                            "_type": "kv",
                            "_attrDef": "p",
                            "_visibility": false
                        },
                        {
                            "_key": "(audioended)",
                            "_value": "",
                            "_type": "kv",
                            "_attrDef": "p",
                            "_visibility": false
                        },
                        {
                            "_key": "(videoended)",
                            "_value": "",
                            "_type": "kv",
                            "_attrDef": "p",
                            "_visibility": false
                        }
                    ],
                    "7fcf325a-bf6a-7772-0841-4a0b0c90d355": {
                        "paletteKey": "html-editor",
                        "parentEditorKey": "643c0549-a468-bcae-b5b6-49138e925b10",
                        "isAdvancedChildComponent": true,
                        "commentid": null,
                        "designerReference": [
                            {
                                "_key": "style",
                                "_value": "",
                                "_type": "kv",
                                "_attrDef": "p"
                            },
                            {
                                "_key": "class",
                                "_value": "",
                                "_type": "dav",
                                "_attrDef": "p"
                            },
                            {
                                "_key": "html",
                                "_value": "",
                                "_type": "a",
                                "_attrDef": "p"
                            }
                        ]
                    }
                }
            },
            "1c97df16-3aa7-41c4-8b77-00c491a830f9": {
                "paletteKey": "FlexLayoutCol",
                "parentEditorKey": "3d9fd14b-63c9-2d5b-a1d8-66749818231a",
                "commentid": null,
                "designerReference": [
                    {
                        "_key": "componentLabel",
                        "_value": "Column",
                        "_type": "kv",
                        "_attrDef": "p",
                        "_useAsLabel": true
                    },
                    {
                        "_key": "style",
                        "_value": "",
                        "_type": "kv",
                        "_attrDef": "p"
                    },
                    {
                        "_key": "class",
                        "_value": "",
                        "_type": "dav",
                        "_attrDef": "p"
                    },
                    {
                        "_key": "fxFlex",
                        "_value": "",
                        "_type": "kv",
                        "_attrDef": "p"
                    },
                    {
                        "_key": "fxLayoutGap",
                        "_value": "",
                        "_type": "kv",
                        "_attrDef": "p"
                    },
                    {
                        "_key": "wrap",
                        "_value": "wrap",
                        "_type": "a",
                        "_attrDef": "p"
                    },
                    {
                        "_key": "layoutAlign",
                        "_value": "start",
                        "_type": "a",
                        "_attrDef": "p"
                    },
                    {
                        "_key": "pLayoutAlign",
                        "_value": "stretch",
                        "_type": "a",
                        "_attrDef": "p"
                    },
                    {
                        "_key": "[fxShow]",
                        "_value": "true",
                        "_type": "kv",
                        "_attrDef": "p"
                    }
                ],
                "7072d88d-dd34-5a33-55a8-75704a8f9ada": {
                    "paletteKey": "Html5",
                    "parentEditorKey": "1c97df16-3aa7-41c4-8b77-00c491a830f9",
                    "isAdvancedComponent": true,
                    "commentid": null,
                    "designerReference": [
                        {
                            "_key": "style",
                            "_value": "",
                            "_type": "kv",
                            "_attrDef": "p"
                        },
                        {
                            "_key": "class",
                            "_value": "",
                            "_type": "dav",
                            "_attrDef": "p"
                        },
                        {
                            "_key": "htmlElement",
                            "_value": "div",
                            "_type": "dav",
                            "_attrDef": "p",
                            "_useAsLabel": true
                        },
                        {
                            "_key": "tagType",
                            "_value": "",
                            "_type": "a",
                            "_attrDef": "p",
                            "_visibility": false
                        },
                        {
                            "_key": "name",
                            "_value": "",
                            "_type": "kv",
                            "_attrDef": "p",
                            "_visibility": false
                        },
                        {
                            "_key": "sandbox",
                            "_value": "",
                            "_type": "kv",
                            "_attrDef": "p",
                            "_visibility": false
                        },
                        {
                            "_key": "src",
                            "_value": "",
                            "_type": "kv",
                            "_attrDef": "p",
                            "_visibility": false
                        },
                        {
                            "_key": "srcdoc",
                            "_value": "",
                            "_type": "kv",
                            "_attrDef": "p",
                            "_visibility": false
                        },
                        {
                            "_key": "width",
                            "_value": "",
                            "_type": "kv",
                            "_attrDef": "p",
                            "_visibility": false
                        },
                        {
                            "_key": "[autoplay]",
                            "_value": "",
                            "_type": "kv",
                            "_attrDef": "p",
                            "_visibility": false
                        },
                        {
                            "_key": "[loop]",
                            "_value": "",
                            "_type": "kv",
                            "_attrDef": "p",
                            "_visibility": false
                        },
                        {
                            "_key": "data",
                            "_value": "",
                            "_type": "kv",
                            "_attrDef": "p",
                            "_visibility": false
                        },
                        {
                            "_key": "audioSource",
                            "_value": [],
                            "_type": "a",
                            "_attrDef": "p",
                            "_visibility": false
                        },
                        {
                            "_key": "videoSource",
                            "_value": [],
                            "_type": "a",
                            "_attrDef": "p",
                            "_visibility": false
                        },
                        {
                            "_key": "audioDatasource",
                            "_value": "",
                            "_type": "a",
                            "_attrDef": "p",
                            "_visibility": false
                        },
                        {
                            "_key": "audioSrc",
                            "_value": "",
                            "_type": "a",
                            "_attrDef": "p",
                            "_visibility": false
                        },
                        {
                            "_key": "audioType",
                            "_value": "",
                            "_type": "a",
                            "_attrDef": "p",
                            "_visibility": false
                        },
                        {
                            "_key": "videoDatasource",
                            "_value": "",
                            "_type": "a",
                            "_attrDef": "p",
                            "_visibility": false
                        },
                        {
                            "_key": "videoSrc",
                            "_value": "",
                            "_type": "a",
                            "_attrDef": "p",
                            "_visibility": false
                        },
                        {
                            "_key": "videoType",
                            "_value": "",
                            "_type": "a",
                            "_attrDef": "p",
                            "_visibility": false
                        },
                        {
                            "_key": "(audioplay)",
                            "_value": "",
                            "_type": "a",
                            "_attrDef": "p",
                            "_visibility": false
                        },
                        {
                            "_key": "(videoplay)",
                            "_value": "",
                            "_type": "a",
                            "_attrDef": "p",
                            "_visibility": false
                        },
                        {
                            "_key": "(audiopause)",
                            "_value": "",
                            "_type": "kv",
                            "_attrDef": "p",
                            "_visibility": false
                        },
                        {
                            "_key": "(videopause)",
                            "_value": "",
                            "_type": "kv",
                            "_attrDef": "p",
                            "_visibility": false
                        },
                        {
                            "_key": "(audioended)",
                            "_value": "",
                            "_type": "kv",
                            "_attrDef": "p",
                            "_visibility": false
                        },
                        {
                            "_key": "(videoended)",
                            "_value": "",
                            "_type": "kv",
                            "_attrDef": "p",
                            "_visibility": false
                        }
                    ],
                    "cefab9e6-a69d-f60c-9cd4-ecd6a496b950": {
                        "paletteKey": "html-editor",
                        "parentEditorKey": "7072d88d-dd34-5a33-55a8-75704a8f9ada",
                        "isAdvancedChildComponent": true,
                        "commentid": null,
                        "designerReference": [
                            {
                                "_key": "style",
                                "_value": "",
                                "_type": "kv",
                                "_attrDef": "p"
                            },
                            {
                                "_key": "class",
                                "_value": "",
                                "_type": "dav",
                                "_attrDef": "p"
                            },
                            {
                                "_key": "html",
                                "_value": "",
                                "_type": "a",
                                "_attrDef": "p"
                            }
                        ]
                    }
                }
            },
            "b425b529-7092-396f-d481-16c0cc021739": {
                "paletteKey": "FlexLayoutCol",
                "parentEditorKey": "3d9fd14b-63c9-2d5b-a1d8-66749818231a",
                "commentid": null,
                "designerReference": [
                    {
                        "_key": "componentLabel",
                        "_value": "Column",
                        "_type": "kv",
                        "_attrDef": "p",
                        "_useAsLabel": true
                    },
                    {
                        "_key": "style",
                        "_value": "",
                        "_type": "kv",
                        "_attrDef": "p"
                    },
                    {
                        "_key": "class",
                        "_value": "",
                        "_type": "dav",
                        "_attrDef": "p"
                    },
                    {
                        "_key": "fxFlex",
                        "_value": "",
                        "_type": "kv",
                        "_attrDef": "p"
                    },
                    {
                        "_key": "fxLayoutGap",
                        "_value": "",
                        "_type": "kv",
                        "_attrDef": "p"
                    },
                    {
                        "_key": "wrap",
                        "_value": "wrap",
                        "_type": "a",
                        "_attrDef": "p"
                    },
                    {
                        "_key": "layoutAlign",
                        "_value": "start",
                        "_type": "a",
                        "_attrDef": "p"
                    },
                    {
                        "_key": "pLayoutAlign",
                        "_value": "stretch",
                        "_type": "a",
                        "_attrDef": "p"
                    },
                    {
                        "_key": "[fxShow]",
                        "_value": "true",
                        "_type": "kv",
                        "_attrDef": "p"
                    }
                ],
                "cbc3af2e-795d-8579-d49a-4cad59668b4e": {
                    "paletteKey": "Html5",
                    "parentEditorKey": "b425b529-7092-396f-d481-16c0cc021739",
                    "isAdvancedComponent": true,
                    "commentid": null,
                    "designerReference": [
                        {
                            "_key": "style",
                            "_value": "",
                            "_type": "kv",
                            "_attrDef": "p"
                        },
                        {
                            "_key": "class",
                            "_value": "",
                            "_type": "dav",
                            "_attrDef": "p"
                        },
                        {
                            "_key": "htmlElement",
                            "_value": "div",
                            "_type": "dav",
                            "_attrDef": "p",
                            "_useAsLabel": true
                        },
                        {
                            "_key": "tagType",
                            "_value": "",
                            "_type": "a",
                            "_attrDef": "p",
                            "_visibility": false
                        },
                        {
                            "_key": "name",
                            "_value": "",
                            "_type": "kv",
                            "_attrDef": "p",
                            "_visibility": false
                        },
                        {
                            "_key": "sandbox",
                            "_value": "",
                            "_type": "kv",
                            "_attrDef": "p",
                            "_visibility": false
                        },
                        {
                            "_key": "src",
                            "_value": "",
                            "_type": "kv",
                            "_attrDef": "p",
                            "_visibility": false
                        },
                        {
                            "_key": "srcdoc",
                            "_value": "",
                            "_type": "kv",
                            "_attrDef": "p",
                            "_visibility": false
                        },
                        {
                            "_key": "width",
                            "_value": "",
                            "_type": "kv",
                            "_attrDef": "p",
                            "_visibility": false
                        },
                        {
                            "_key": "[autoplay]",
                            "_value": "",
                            "_type": "kv",
                            "_attrDef": "p",
                            "_visibility": false
                        },
                        {
                            "_key": "[loop]",
                            "_value": "",
                            "_type": "kv",
                            "_attrDef": "p",
                            "_visibility": false
                        },
                        {
                            "_key": "data",
                            "_value": "",
                            "_type": "kv",
                            "_attrDef": "p",
                            "_visibility": false
                        },
                        {
                            "_key": "audioSource",
                            "_value": [],
                            "_type": "a",
                            "_attrDef": "p",
                            "_visibility": false
                        },
                        {
                            "_key": "videoSource",
                            "_value": [],
                            "_type": "a",
                            "_attrDef": "p",
                            "_visibility": false
                        },
                        {
                            "_key": "audioDatasource",
                            "_value": "",
                            "_type": "a",
                            "_attrDef": "p",
                            "_visibility": false
                        },
                        {
                            "_key": "audioSrc",
                            "_value": "",
                            "_type": "a",
                            "_attrDef": "p",
                            "_visibility": false
                        },
                        {
                            "_key": "audioType",
                            "_value": "",
                            "_type": "a",
                            "_attrDef": "p",
                            "_visibility": false
                        },
                        {
                            "_key": "videoDatasource",
                            "_value": "",
                            "_type": "a",
                            "_attrDef": "p",
                            "_visibility": false
                        },
                        {
                            "_key": "videoSrc",
                            "_value": "",
                            "_type": "a",
                            "_attrDef": "p",
                            "_visibility": false
                        },
                        {
                            "_key": "videoType",
                            "_value": "",
                            "_type": "a",
                            "_attrDef": "p",
                            "_visibility": false
                        },
                        {
                            "_key": "(audioplay)",
                            "_value": "",
                            "_type": "a",
                            "_attrDef": "p",
                            "_visibility": false
                        },
                        {
                            "_key": "(videoplay)",
                            "_value": "",
                            "_type": "a",
                            "_attrDef": "p",
                            "_visibility": false
                        },
                        {
                            "_key": "(audiopause)",
                            "_value": "",
                            "_type": "kv",
                            "_attrDef": "p",
                            "_visibility": false
                        },
                        {
                            "_key": "(videopause)",
                            "_value": "",
                            "_type": "kv",
                            "_attrDef": "p",
                            "_visibility": false
                        },
                        {
                            "_key": "(audioended)",
                            "_value": "",
                            "_type": "kv",
                            "_attrDef": "p",
                            "_visibility": false
                        },
                        {
                            "_key": "(videoended)",
                            "_value": "",
                            "_type": "kv",
                            "_attrDef": "p",
                            "_visibility": false
                        }
                    ],
                    "afd6f03a-4534-7a8e-8cec-21a75ee8a29c": {
                        "paletteKey": "html-editor",
                        "parentEditorKey": "cbc3af2e-795d-8579-d49a-4cad59668b4e",
                        "isAdvancedChildComponent": true,
                        "commentid": null,
                        "designerReference": [
                            {
                                "_key": "style",
                                "_value": "",
                                "_type": "kv",
                                "_attrDef": "p"
                            },
                            {
                                "_key": "class",
                                "_value": "",
                                "_type": "dav",
                                "_attrDef": "p"
                            },
                            {
                                "_key": "html",
                                "_value": "",
                                "_type": "a",
                                "_attrDef": "p"
                            }
                        ]
                    }
                }
            },
            "1b59b42c-d8bf-2d47-c8de-082eefaba465": {
                "paletteKey": "FlexLayoutCol",
                "parentEditorKey": "3d9fd14b-63c9-2d5b-a1d8-66749818231a",
                "commentid": null,
                "designerReference": [
                    {
                        "_key": "componentLabel",
                        "_value": "Column",
                        "_type": "kv",
                        "_attrDef": "p",
                        "_useAsLabel": true
                    },
                    {
                        "_key": "style",
                        "_value": "",
                        "_type": "kv",
                        "_attrDef": "p"
                    },
                    {
                        "_key": "class",
                        "_value": "",
                        "_type": "dav",
                        "_attrDef": "p"
                    },
                    {
                        "_key": "fxFlex",
                        "_value": "",
                        "_type": "kv",
                        "_attrDef": "p"
                    },
                    {
                        "_key": "fxLayoutGap",
                        "_value": "",
                        "_type": "kv",
                        "_attrDef": "p"
                    },
                    {
                        "_key": "wrap",
                        "_value": "wrap",
                        "_type": "a",
                        "_attrDef": "p"
                    },
                    {
                        "_key": "layoutAlign",
                        "_value": "start",
                        "_type": "a",
                        "_attrDef": "p"
                    },
                    {
                        "_key": "pLayoutAlign",
                        "_value": "stretch",
                        "_type": "a",
                        "_attrDef": "p"
                    },
                    {
                        "_key": "[fxShow]",
                        "_value": "true",
                        "_type": "kv",
                        "_attrDef": "p"
                    }
                ],
                "ea5e1154-f90d-d303-c80d-37094af3d92b": {
                    "paletteKey": "Html5",
                    "parentEditorKey": "1b59b42c-d8bf-2d47-c8de-082eefaba465",
                    "isAdvancedComponent": true,
                    "commentid": null,
                    "designerReference": [
                        {
                            "_key": "style",
                            "_value": "",
                            "_type": "kv",
                            "_attrDef": "p"
                        },
                        {
                            "_key": "class",
                            "_value": "",
                            "_type": "dav",
                            "_attrDef": "p"
                        },
                        {
                            "_key": "htmlElement",
                            "_value": "div",
                            "_type": "dav",
                            "_attrDef": "p",
                            "_useAsLabel": true
                        },
                        {
                            "_key": "tagType",
                            "_value": "",
                            "_type": "a",
                            "_attrDef": "p",
                            "_visibility": false
                        },
                        {
                            "_key": "name",
                            "_value": "",
                            "_type": "kv",
                            "_attrDef": "p",
                            "_visibility": false
                        },
                        {
                            "_key": "sandbox",
                            "_value": "",
                            "_type": "kv",
                            "_attrDef": "p",
                            "_visibility": false
                        },
                        {
                            "_key": "src",
                            "_value": "",
                            "_type": "kv",
                            "_attrDef": "p",
                            "_visibility": false
                        },
                        {
                            "_key": "srcdoc",
                            "_value": "",
                            "_type": "kv",
                            "_attrDef": "p",
                            "_visibility": false
                        },
                        {
                            "_key": "width",
                            "_value": "",
                            "_type": "kv",
                            "_attrDef": "p",
                            "_visibility": false
                        },
                        {
                            "_key": "[autoplay]",
                            "_value": "",
                            "_type": "kv",
                            "_attrDef": "p",
                            "_visibility": false
                        },
                        {
                            "_key": "[loop]",
                            "_value": "",
                            "_type": "kv",
                            "_attrDef": "p",
                            "_visibility": false
                        },
                        {
                            "_key": "data",
                            "_value": "",
                            "_type": "kv",
                            "_attrDef": "p",
                            "_visibility": false
                        },
                        {
                            "_key": "audioSource",
                            "_value": [],
                            "_type": "a",
                            "_attrDef": "p",
                            "_visibility": false
                        },
                        {
                            "_key": "videoSource",
                            "_value": [],
                            "_type": "a",
                            "_attrDef": "p",
                            "_visibility": false
                        },
                        {
                            "_key": "audioDatasource",
                            "_value": "",
                            "_type": "a",
                            "_attrDef": "p",
                            "_visibility": false
                        },
                        {
                            "_key": "audioSrc",
                            "_value": "",
                            "_type": "a",
                            "_attrDef": "p",
                            "_visibility": false
                        },
                        {
                            "_key": "audioType",
                            "_value": "",
                            "_type": "a",
                            "_attrDef": "p",
                            "_visibility": false
                        },
                        {
                            "_key": "videoDatasource",
                            "_value": "",
                            "_type": "a",
                            "_attrDef": "p",
                            "_visibility": false
                        },
                        {
                            "_key": "videoSrc",
                            "_value": "",
                            "_type": "a",
                            "_attrDef": "p",
                            "_visibility": false
                        },
                        {
                            "_key": "videoType",
                            "_value": "",
                            "_type": "a",
                            "_attrDef": "p",
                            "_visibility": false
                        },
                        {
                            "_key": "(audioplay)",
                            "_value": "",
                            "_type": "a",
                            "_attrDef": "p",
                            "_visibility": false
                        },
                        {
                            "_key": "(videoplay)",
                            "_value": "",
                            "_type": "a",
                            "_attrDef": "p",
                            "_visibility": false
                        },
                        {
                            "_key": "(audiopause)",
                            "_value": "",
                            "_type": "kv",
                            "_attrDef": "p",
                            "_visibility": false
                        },
                        {
                            "_key": "(videopause)",
                            "_value": "",
                            "_type": "kv",
                            "_attrDef": "p",
                            "_visibility": false
                        },
                        {
                            "_key": "(audioended)",
                            "_value": "",
                            "_type": "kv",
                            "_attrDef": "p",
                            "_visibility": false
                        },
                        {
                            "_key": "(videoended)",
                            "_value": "",
                            "_type": "kv",
                            "_attrDef": "p",
                            "_visibility": false
                        }
                    ],
                    "89bf9e63-2614-bab8-67d3-90e3dd4a16d5": {
                        "paletteKey": "html-editor",
                        "parentEditorKey": "ea5e1154-f90d-d303-c80d-37094af3d92b",
                        "isAdvancedChildComponent": true,
                        "commentid": null,
                        "designerReference": [
                            {
                                "_key": "style",
                                "_value": "",
                                "_type": "kv",
                                "_attrDef": "p"
                            },
                            {
                                "_key": "class",
                                "_value": "",
                                "_type": "dav",
                                "_attrDef": "p"
                            },
                            {
                                "_key": "html",
                                "_value": "",
                                "_type": "a",
                                "_attrDef": "p"
                            }
                        ]
                    }
                }
            }
        },
        "1a758e02-8254-3c5d-dbd1-35aa64081002": {
            "paletteKey": "FlexLayoutCol",
            "parentEditorKey": "89bbd920-f9c6-f1ee-242f-3626b04d0141",
            "commentid": null,
            "designerReference": [
                {
                    "_key": "componentLabel",
                    "_value": "Column",
                    "_type": "kv",
                    "_attrDef": "p",
                    "_useAsLabel": true
                },
                {
                    "_key": "style",
                    "_value": "",
                    "_type": "kv",
                    "_attrDef": "p"
                },
                {
                    "_key": "class",
                    "_value": "",
                    "_type": "dav",
                    "_attrDef": "p"
                },
                {
                    "_key": "fxFlex",
                    "_value": "",
                    "_type": "kv",
                    "_attrDef": "p"
                },
                {
                    "_key": "fxLayoutGap",
                    "_value": "",
                    "_type": "kv",
                    "_attrDef": "p"
                },
                {
                    "_key": "wrap",
                    "_value": "wrap",
                    "_type": "a",
                    "_attrDef": "p"
                },
                {
                    "_key": "layoutAlign",
                    "_value": "start",
                    "_type": "a",
                    "_attrDef": "p"
                },
                {
                    "_key": "pLayoutAlign",
                    "_value": "stretch",
                    "_type": "a",
                    "_attrDef": "p"
                },
                {
                    "_key": "[fxShow]",
                    "_value": "true",
                    "_type": "kv",
                    "_attrDef": "p"
                }
            ]
        }
    }
}
